hand_dim/__init__.py
hand_dim/hand_dim.py
hand_dim-0.1.0.dist-info/METADATA
hand_dim-0.1.0.dist-info/WHEEL
hand_dim-0.1.0.dist-info/top_level.txt
hand_dim-0.1.0.dist-info/RECORD
