Metadata-Version: 2.1
Name: hand-dim
Version: 0.1.0
Summary: A package to calculate hand dimensions based on head length
Home-page: https://github.com/yourusername/hand_dim
Author: YDeepesh Gora
Author-email: deepeshgorai13@gmail.com
Classifier: Programming Language :: Python :: 3
Classifier: License :: OSI Approved :: MIT License
Classifier: Operating System :: OS Independent
Requires-Python: >=3.6
